moipg/__init__.py
moipg/test.py
moipg/vtons.py
moipg/IDM_VTON/__init__.py
moipg/IDM_VTON/gradio_demo/__init__.py
moipg/IDM_VTON/gradio_demo/app.py
moipg/IDM_VTON/gradio_demo/apple.py
moipg/IDM_VTON/gradio_demo/apply_net.py
moipg/IDM_VTON/gradio_demo/utils_mask.py
moipg/IDM_VTON/gradio_demo/densepose/__init__.py
moipg/IDM_VTON/gradio_demo/densepose/config.py
moipg/IDM_VTON/gradio_demo/densepose/converters/__init__.py
moipg/IDM_VTON/gradio_demo/densepose/converters/base.py
moipg/IDM_VTON/gradio_demo/densepose/converters/builtin.py
moipg/IDM_VTON/gradio_demo/densepose/converters/chart_output_hflip.py
moipg/IDM_VTON/gradio_demo/densepose/converters/chart_output_to_chart_result.py
moipg/IDM_VTON/gradio_demo/densepose/converters/hflip.py
moipg/IDM_VTON/gradio_demo/densepose/converters/segm_to_mask.py
moipg/IDM_VTON/gradio_demo/densepose/converters/to_chart_result.py
moipg/IDM_VTON/gradio_demo/densepose/converters/to_mask.py
moipg/IDM_VTON/gradio_demo/densepose/data/__init__.py
moipg/IDM_VTON/gradio_demo/densepose/data/build.py
moipg/IDM_VTON/gradio_demo/densepose/data/combined_loader.py
moipg/IDM_VTON/gradio_demo/densepose/data/dataset_mapper.py
moipg/IDM_VTON/gradio_demo/densepose/data/image_list_dataset.py
moipg/IDM_VTON/gradio_demo/densepose/data/inference_based_loader.py
moipg/IDM_VTON/gradio_demo/densepose/data/utils.py
moipg/IDM_VTON/gradio_demo/densepose/data/datasets/__init__.py
moipg/IDM_VTON/gradio_demo/densepose/data/datasets/builtin.py
moipg/IDM_VTON/gradio_demo/densepose/data/datasets/chimpnsee.py
moipg/IDM_VTON/gradio_demo/densepose/data/datasets/coco.py
moipg/IDM_VTON/gradio_demo/densepose/data/datasets/dataset_type.py
moipg/IDM_VTON/gradio_demo/densepose/data/datasets/lvis.py
moipg/IDM_VTON/gradio_demo/densepose/data/meshes/__init__.py
moipg/IDM_VTON/gradio_demo/densepose/data/meshes/builtin.py
moipg/IDM_VTON/gradio_demo/densepose/data/meshes/catalog.py
moipg/IDM_VTON/gradio_demo/densepose/data/samplers/__init__.py
moipg-0.0.8.dist-info/METADATA
moipg-0.0.8.dist-info/WHEEL
moipg-0.0.8.dist-info/top_level.txt
moipg-0.0.8.dist-info/RECORD
